LICENSE
MANIFEST.in
README.rst
setup.cfg
setup.py
django_netbox_graphql.egg-info/PKG-INFO
django_netbox_graphql.egg-info/SOURCES.txt
django_netbox_graphql.egg-info/dependency_links.txt
django_netbox_graphql.egg-info/requires.txt
django_netbox_graphql.egg-info/top_level.txt
netbox_graphql/__init__.py
netbox_graphql/circuits_schema.py
netbox_graphql/custom_filter_fields.py
netbox_graphql/dcim_schema.py
netbox_graphql/helper_methods.py
netbox_graphql/ipam_schema.py
netbox_graphql/schema.py
netbox_graphql/tenancy_schema.py
netbox_graphql/urls.py
netbox_graphql/virtualization_schema.py
netbox_graphql/tests/__init__.py
netbox_graphql/tests/utils.py
netbox_graphql/tests/circuits/__init__.py
netbox_graphql/tests/circuits/tests_circuits.py
netbox_graphql/tests/circuits/tests_providers.py
netbox_graphql/tests/circuits/tests_terminations.py
netbox_graphql/tests/circuits/tests_types.py
netbox_graphql/tests/dcim/__init__.py
netbox_graphql/tests/dcim/tests_regions.py
netbox_graphql/tests/dcim/tests_sites.py
netbox_graphql/tests/factories/__init__.py
netbox_graphql/tests/factories/circuit_factories.py
netbox_graphql/tests/factories/dcim_factories.py
netbox_graphql/tests/factories/ipam_factories.py
netbox_graphql/tests/factories/tenant_factories.py
netbox_graphql/tests/factories/virtualization_factories.py
netbox_graphql/tests/ipam/__init__.py
netbox_graphql/tests/ipam/tests_aggregates.py
netbox_graphql/tests/ipam/tests_ip_addresses.py
netbox_graphql/tests/ipam/tests_prefixes.py
netbox_graphql/tests/ipam/tests_rirs.py
netbox_graphql/tests/ipam/tests_roles.py
netbox_graphql/tests/ipam/tests_vlan_groups.py
netbox_graphql/tests/ipam/tests_vlans.py
netbox_graphql/tests/ipam/tests_vrfs.py
netbox_graphql/tests/tenancy/__init__.py
netbox_graphql/tests/tenancy/tests_groups.py
netbox_graphql/tests/tenancy/tests_tenants.py
netbox_graphql/tests/virtualization/__init__.py
netbox_graphql/tests/virtualization/tests_cluster_groups.py
netbox_graphql/tests/virtualization/tests_cluster_types.py
netbox_graphql/tests/virtualization/tests_clusters.py
netbox_graphql/tests/virtualization/tests_virtual_machines.py